keboola/http_client/__init__.py
keboola/http_client/http.py
keboola.http_client-1.0.1.dist-info/LICENSE
keboola.http_client-1.0.1.dist-info/METADATA
keboola.http_client-1.0.1.dist-info/WHEEL
keboola.http_client-1.0.1.dist-info/top_level.txt
keboola.http_client-1.0.1.dist-info/RECORD
