Metadata-Version: 2.1
Name: keboola.http-client
Version: 1.0.1
Summary: General HTTP requests library for Python applications running in Keboola Connection environment
Home-page: https://github.com/keboola/python-http-client
Author: Keboola KDS Team
Author-email: support@keboola.com
License: UNKNOWN
Project-URL: Documentation, https://htmlpreview.github.io/?https://raw.githubusercontent.com/keboola/python-http-client/main/docs/api-html/http_client/http.html
Platform: UNKNOWN
Classifier: Programming Language :: Python :: 3
Classifier: License :: OSI Approved :: MIT License
Classifier: Operating System :: OS Independent
Classifier: Intended Audience :: Developers
Classifier: Intended Audience :: Information Technology
Classifier: Intended Audience :: Education
Classifier: Topic :: Software Development :: Libraries
Classifier: Topic :: Software Development :: Libraries :: Python Modules
Classifier: Development Status :: 4 - Beta
Requires-Python: >=3.7
Requires-Dist: requests
